mantisdk/__init__.py
mantisdk/client.py
mantisdk/config.py
mantisdk/env_var.py
mantisdk/llm_proxy.py
mantisdk/logging.py
mantisdk/reward.py
mantisdk/semconv.py
mantisdk/server.py
mantisdk/adapter/__init__.py
mantisdk/adapter/base.py
mantisdk/adapter/messages.py
mantisdk/adapter/triplet.py
mantisdk/algorithm/__init__.py
mantisdk/algorithm/base.py
mantisdk/algorithm/decorator.py
mantisdk/algorithm/fast.py
mantisdk/algorithm/utils.py
mantisdk/algorithm/apo/__init__.py
mantisdk/algorithm/apo/apo.py
mantisdk/algorithm/apo/prompts/apply_edit_variant01.poml
mantisdk/algorithm/apo/prompts/apply_edit_variant02.poml
mantisdk/algorithm/apo/prompts/text_gradient_variant01.poml
mantisdk/algorithm/apo/prompts/text_gradient_variant02.poml
mantisdk/algorithm/apo/prompts/text_gradient_variant03.poml
mantisdk/algorithm/gepa/__init__.py
mantisdk/algorithm/gepa/adapter.py
mantisdk/algorithm/gepa/gepa.py
mantisdk/algorithm/gepa/tracing.py
mantisdk/algorithm/gepa/lib/__init__.py
mantisdk/algorithm/gepa/lib/api.py
mantisdk/algorithm/gepa/lib/gepa_utils.py
mantisdk/algorithm/gepa/lib/py.typed
mantisdk/algorithm/gepa/lib/adapters/README.md
mantisdk/algorithm/gepa/lib/adapters/__init__.py
mantisdk/algorithm/gepa/lib/adapters/anymaths_adapter/README.md
mantisdk/algorithm/gepa/lib/adapters/anymaths_adapter/__init__.py
mantisdk/algorithm/gepa/lib/adapters/anymaths_adapter/anymaths_adapter.py
mantisdk/algorithm/gepa/lib/adapters/anymaths_adapter/requirements.txt
mantisdk/algorithm/gepa/lib/adapters/default_adapter/README.md
mantisdk/algorithm/gepa/lib/adapters/default_adapter/__init__.py
mantisdk/algorithm/gepa/lib/adapters/default_adapter/default_adapter.py
mantisdk/algorithm/gepa/lib/adapters/dspy_adapter/README.md
mantisdk/algorithm/gepa/lib/adapters/dspy_adapter/__init__.py
mantisdk/algorithm/gepa/lib/adapters/dspy_adapter/dspy_adapter.py
mantisdk/algorithm/gepa/lib/adapters/dspy_full_program_adapter/README.md
mantisdk-0.1.3.dist-info/METADATA
mantisdk-0.1.3.dist-info/WHEEL
mantisdk-0.1.3.dist-info/entry_points.txt
mantisdk-0.1.3.dist-info/licenses/LICENSE
mantisdk-0.1.3.dist-info/RECORD
