Metadata-Version: 2.4
Name: mantisdk
Version: 0.1.3
Summary: Mantisdk - AI Agent Training and Evaluation Platform
Project-URL: Homepage, https://github.com/withmetis/mantis
Project-URL: Documentation, https://withmetis.github.io/mantis/mantisdk/
Project-URL: Repository, https://github.com/withmetis/mantis
Project-URL: Issues, https://github.com/withmetis/mantis/issues
Author-email: Metis Team <team@withmetis.ai>
License: MIT
License-File: LICENSE
Keywords: agents,ai,evaluation,llm,mantis,observability,reinforcement-learning,training
Classifier: Development Status :: 4 - Beta
Classifier: Intended Audience :: Developers
Classifier: License :: OSI Approved :: MIT License
Classifier: Programming Language :: Python :: 3
Classifier: Programming Language :: Python :: 3.10
Classifier: Programming Language :: Python :: 3.11
Classifier: Programming Language :: Python :: 3.12
Classifier: Topic :: Scientific/Engineering :: Artificial Intelligence
Requires-Python: >=3.10
Requires-Dist: aiohttp
Requires-Dist: aiologic
Requires-Dist: fastapi
Requires-Dist: flask
Requires-Dist: gepa>=0.0.24
Requires-Dist: gpustat
Requires-Dist: graphviz
Requires-Dist: gunicorn
Requires-Dist: litellm[proxy]>=1.74
Requires-Dist: openai
Requires-Dist: opentelemetry-api>=1.35
Requires-Dist: opentelemetry-exporter-otlp>=1.35
Requires-Dist: opentelemetry-sdk>=1.35
Requires-Dist: portpicker
Requires-Dist: psutil
Requires-Dist: pydantic>=2.11
Requires-Dist: rich
Requires-Dist: setproctitle
Requires-Dist: uvicorn
Requires-Dist: uvicorn-worker
Provides-Extra: apo
Requires-Dist: poml; extra == 'apo'
Provides-Extra: mongo
Requires-Dist: pymongo; extra == 'mongo'
Provides-Extra: verl
Requires-Dist: verl>=0.5.0; extra == 'verl'
Requires-Dist: vllm>=0.8.4; extra == 'verl'
Provides-Extra: weave
Requires-Dist: weave>=0.52.22; extra == 'weave'
